pyamg/__init__.py
pyamg/blackbox.py
pyamg/graph.py
pyamg/graph_ref.py
pyamg/multilevel.py
pyamg/strength.py
pyamg/version.py
pyamg/aggregation/__init__.py
pyamg/aggregation/adaptive.py
pyamg/aggregation/aggregate.py
pyamg/aggregation/aggregation.py
pyamg/aggregation/pairwise.py
pyamg/aggregation/rootnode.py
pyamg/aggregation/smooth.py
pyamg/aggregation/tentative.py
pyamg/aggregation/tests/__init__.py
pyamg/aggregation/tests/test_adaptive.py
pyamg/aggregation/tests/test_aggregate.py
pyamg/aggregation/tests/test_aggregation.py
pyamg/aggregation/tests/test_pairwise.py
pyamg/aggregation/tests/test_rootnode.py
pyamg/aggregation/tests/test_smooth.py
pyamg/aggregation/tests/test_tentative.py
pyamg/amg_core/__init__.py
pyamg/amg_core/air.cp311-win_amd64.pyd
pyamg/amg_core/bindthem.py
pyamg/amg_core/evolution_strength.cp311-win_amd64.pyd
pyamg/amg_core/graph.cp311-win_amd64.pyd
pyamg/amg_core/krylov.cp311-win_amd64.pyd
pyamg/amg_core/linalg.cp311-win_amd64.pyd
pyamg/amg_core/relaxation.cp311-win_amd64.pyd
pyamg/amg_core/ruge_stuben.cp311-win_amd64.pyd
pyamg/amg_core/smoothed_aggregation.cp311-win_amd64.pyd
pyamg/amg_core/tests/__init__.py
pyamg/amg_core/tests/bind_examples.cp311-win_amd64.pyd
pyamg/amg_core/tests/test_bind_examples.py
pyamg/classical/__init__.py
pyamg/classical/air.py
pyamg/classical/classical.py
pyamg/classical/cr.py
pyamg/classical/interpolate.py
pyamg/classical/split.py
pyamg/classical/tests/__init__.py
pyamg/classical/tests/test_air.py
pyamg/classical/tests/test_classical.py
pyamg/classical/tests/test_cr.py
pyamg/classical/tests/test_split.py
pyamg/gallery/__init__.py
pyamg/gallery/advection.py
pyamg/gallery/demo.py
pyamg/gallery/diffusion.py
pyamg/gallery/elasticity.py
pyamg/gallery/example.py
pyamg/gallery/fem.py
pyamg/gallery/laplacian.py
pyamg/gallery/mesh.py
pyamg/gallery/random_sparse.py
pyamg/gallery/stencil.py
pyamg/gallery/example_data/airfoil.mat
pyamg/gallery/example_data/bar.mat
pyamg/gallery/example_data/helmholtz_2D.mat
pyamg-5.3.0.dist-info/licenses/LICENSE.txt
pyamg-5.3.0.dist-info/METADATA
pyamg-5.3.0.dist-info/WHEEL
pyamg-5.3.0.dist-info/top_level.txt
pyamg-5.3.0.dist-info/RECORD
