Metadata-Version: 2.4
Name: pyamg
Version: 5.3.0
Summary: PyAMG: Algebraic Multigrid Solvers in Python
Home-page: https://github.com/pyamg/pyamg
Download-URL: https://github.com/pyamg/pyamg/releases
Author: Nathan Bell, Luke Olson, and Jacob Schroder
Author-email: luke.olson@gmail.com
Maintainer: Luke Olson
Maintainer-email: luke.olson@gmail.com
License: MIT
Keywords: algebraic multigrid,AMG,sparse matrix,preconditioning
Classifier: Development Status :: 5 - Production/Stable
Classifier: Intended Audience :: Developers
Classifier: Intended Audience :: Education
Classifier: Intended Audience :: Science/Research
Classifier: License :: OSI Approved :: MIT License
Classifier: Natural Language :: English
Classifier: Operating System :: OS Independent
Classifier: Programming Language :: C++
Classifier: Programming Language :: Python
Classifier: Programming Language :: Python :: 3
Classifier: Programming Language :: Python :: 3.9
Classifier: Programming Language :: Python :: 3.10
Classifier: Programming Language :: Python :: 3.11
Classifier: Programming Language :: Python :: 3.12
Classifier: Topic :: Education
Classifier: Topic :: Scientific/Engineering
Classifier: Topic :: Scientific/Engineering :: Mathematics
Classifier: Topic :: Software Development :: Libraries :: Python Modules
Requires-Python: >=3.9
License-File: LICENSE.txt
Requires-Dist: numpy
Requires-Dist: scipy>=1.11.0
Dynamic: download-url
Dynamic: license-file
